atlas_agent/__init__.py
atlas_agent/__main__.py
atlas_agent/camera_director_templates.py
atlas_agent/capabilities_prompt.py
atlas_agent/chat_rpc_team.py
atlas_agent/cli.py
atlas_agent/codegen_allowlist.txt
atlas_agent/codegen_policy.py
atlas_agent/console_ui.py
atlas_agent/defaults.py
atlas_agent/describe.py
atlas_agent/discovery.py
atlas_agent/easing.py
atlas_agent/exporter.py
atlas_agent/gateway_model.py
atlas_agent/llm_usage.py
atlas_agent/provider_tool_schema.py
atlas_agent/repo.py
atlas_agent/responses_tool_loop.py
atlas_agent/scene_rpc.py
atlas_agent/session_resume.py
atlas_agent/session_store.py
atlas_agent/subprocess_utils.py
atlas_agent/tool_registry.py
atlas_agent/agent_team/__init__.py
atlas_agent/agent_team/base.py
atlas_agent/agent_team/intent_resolver.py
atlas_agent/agent_team/tools_agent.py
atlas_agent/agent_team/tool_modules/__init__.py
atlas_agent/agent_team/tool_modules/animation_tools.py
atlas_agent/agent_team/tool_modules/artifact_tools.py
atlas_agent/agent_team/tool_modules/camera_tools.py
atlas_agent/agent_team/tool_modules/context.py
atlas_agent/agent_team/tool_modules/docs_tools.py
atlas_agent/agent_team/tool_modules/file_formats.py
atlas_agent/agent_team/tool_modules/fs_tools.py
atlas_agent/agent_team/tool_modules/general_tools.py
atlas_agent/agent_team/tool_modules/plan_tools.py
atlas_agent/agent_team/tool_modules/preconditions.py
atlas_agent/agent_team/tool_modules/scene_tools.py
atlas_agent/agent_team/tool_modules/schemas_camera_value.py
atlas_agent/agent_team/tool_modules/session_tools.py
atlas_agent/agent_team/tool_modules/verification_tools.py
atlas_agent/api/__init__.py
atlas_agent/api/camera.py
atlas_agent/api/fs.py
atlas_agent/api/plan_types.py
atlas_agent/api/runner.py
atlas_agent/api/scene.py
atlas_agent/tooling/adapter.py
atlas_agent-1.0.3.dist-info/METADATA
atlas_agent-1.0.3.dist-info/WHEEL
atlas_agent-1.0.3.dist-info/entry_points.txt
atlas_agent-1.0.3.dist-info/top_level.txt
atlas_agent-1.0.3.dist-info/RECORD
