Metadata-Version: 2.4
Name: atlas-agent
Version: 1.0.3
Summary: CLI to operate Atlas via gRPC, with LLM-powered planning, tooling, and verification.
Author: Feng Lab
License: Apache-2.0
Project-URL: Homepage, https://github.com/feng-lab/atlas
Keywords: atlas,grpc,llm,agent,animation,visualization
Classifier: Programming Language :: Python :: 3
Classifier: Programming Language :: Python :: 3 :: Only
Classifier: Programming Language :: Python :: 3.12
Classifier: License :: OSI Approved :: Apache Software License
Classifier: Operating System :: OS Independent
Requires-Python: >=3.12
Requires-Dist: openai>=1.0.0
Requires-Dist: grpcio>=1.56.0
Requires-Dist: grpcio-tools>=1.56.0
Requires-Dist: protobuf>=4.24.0
Requires-Dist: jsonschema>=4.18.0
Requires-Dist: rich>=13.7.0
